{
    "1": {
        "English_v1": "weybrode",
        "French": "plauntayne",
        "Latin_v1": "arnoglossa"
    },
    "2": {
        "English_v1": "horwnde",
        "French": "maroyl",
        "Latin_v1": "marrubium"
    },
    "3": {
        "English_v1": "pude",
        "French": "bugle",
        "Latin_v1": "puclosa"
    },
    "4": {
        "English_v1": "merche",
        "French": "hache",
        "Latin_v1": "apium"
    },
    "5": {
        "English_v1": "viflef",
        "French": "cincfoille",
        "Latin_v1": "quinquefolium"
    },
    "6": {
        "English_v1": "wodemerche",
        "French": "sanicle",
        "Latin_v1": "saniculum"
    },
    "7": {
        "English_v1": "wodemerche",
        "French": "senevey",
        "Latin_v1": "synapis"
    },
    "8": {
        "English_v1": "mynte",
        "French": "mente",
        "Latin_v1": "menta"
    },
    "9": {
        "English_v1": "myxplonte",
        "French": "morele",
        "Latin_v1": "morella"
    },
    "10": {
        "English_v1": "mugwrt",
        "French": "armoes",
        "Latin_v1": "artemesia"
    },
    "11": {
        "English_v1": "wermod",
        "French": "aloyne",
        "Latin_v1": "absinthium"
    },
    "12": {
        "English_v1": "gretwort",
        "English_v2": "scabbewort",
        "French": "alne",
        "Latin_v1": "alna"
    },
    "13": {
        "English_v1": "betonie",
        "French": "vetoine",
        "Latin_v1": "betonica"
    },
    "14": {
        "English_v1": "fille",
        "French": "cerfoille",
        "Latin_v1": "cerefolium"
    },
    "15": {
        "English_v1": "sot",
        "French": "swye",
        "Latin_v1": "fuligo"
    },
    "16": {
        "English_v1": "suþrenewode",
        "French": "averoyne",
        "Latin_v1": "abrotanum"
    },
    "17": {
        "English_v1": "dyle",
        "French": "aneit",
        "Latin_v1": "anetum"
    },
    "18": {
        "English_v1": "horsemynte",
        "French": "mentastre",
        "Latin_v1": "mentastrurn"
    },
    "19": {
        "English_v1": "galloc",
        "French": "confirie",
        "Latin_v1": "confiria"
    },
    "20": {
        "English_v1": "luvestiche",
        "French": "luvache",
        "Latin_v1": "lubesticum"
    },
    "21": {
        "English_v1": "grundeswylie",
        "French": "senesun",
        "Latin_v1": "senecio"
    },
    "22": {
        "English_v1": "medewort",
        "French": "reyne",
        "Latin_v1": "regina"
    },
    "23": {
        "English_v1": "wodesure",
        "French": "payn kuku",
        "Latin_v1": "panis kukuli"
    },
    "24": {
        "English_v1": "blinde netle",
        "French": "morte urtye",
        "Latin_v1": "archangelica"
    },
    "25": {
        "English_v1": "remmesfot",
        "French": "pepol",
        "Latin_v1": "pes pulli"
    },
    "26": {
        "English_v1": "crowes(l)ope",
        "Latin_v1": "savenella"
    },
    "27": {
        "English_v1": "clote",
        "French": "gletenere",
        "Latin_v1": "glutum"
    },
    "28": {
        "English_v1": "everfern",
        "French": "feugerole",
        "Latin_v1": "filex arboratica",
        "Latin_v2": "polipodium "
    },
    "29": {
        "English_v1": "heuppe",
        "French": "butuner",
        "Latin_v1": "butinius"
    },
    "30": {
        "English_v1": "tunkerse",
        "French": "kersun",
        "Latin_v1": "nasturacium"
    },
    "31": {
        "English_v1": "tunkerse",
        "French": "alissaundre",
        "Latin_v1": "olerosa"
    },
    "32": {
        "English_v1": "tunkerse",
        "French": "celydoyne",
        "Latin_v1": "celidonius"
    },
    "33": {
        "English_v1": "nep",
        "French": "navet",
        "Latin_v1": "napus"
    },
    "34": {
        "English_v1": "parvenke",
        "French": "vynne",
        "Latin_v1": "vinea"
    },
    "35": {
        "English_v1": "gladene",
        "French": "glaiol",
        "Latin_v1": "gladiolum"
    },
    "36": {
        "English_v1": "veþervoye",
        "French": "feverfoil",
        "Latin_v1": "febrifugia"
    },
    "37": {
        "English_v1": "tanesy",
        "Latin_v1": "tanazetum"
    },
    "38": {
        "English_v1": "tanesy",
        "French": "waraunce",
        "Latin_v1": "vermiculi"
    },
    "39": {
        "English_v1": "radich",
        "French": "rayz",
        "Latin_v1": "raphanum"
    },
    "40": {
        "English_v1": "sewor",
        "Latin_v1": "alga"
    },
    "41": {
        "English_v1": "sewor",
        "French": "sparge",
        "Latin_v1": "herba munda"
    },
    "42": {
        "English_v1": "sewor",
        "French": "lavendre",
        "Latin_v1": "spika"
    },
    "43": {
        "English_v1": "hemelok",
        "Latin_v1": "ascolonya"
    },
    "44": {
        "English_v1": "lek",
        "Latin_v1": "ambila"
    },
    "45": {
        "English_v1": "hyndeberye",
        "Latin_v1": "acinus"
    },
    "46": {
        "English_v1": "hyndehalethe",
        "Latin_v1": "ambroria"
    },
    "47": {
        "English_v1": "mugwort",
        "Latin_v1": "artemesya"
    },
    "48": {
        "English_v1": "gloswort",
        "Latin_v1": "apollinaris"
    },
    "49": {
        "English_v1": "balso popy",
        "Latin_v1": "astula regia"
    },
    "50": {
        "English_v1": "garlek",
        "Latin_v1": "acetula"
    },
    "51": {
        "English_v1": "blewort",
        "Latin_v1": "acantan"
    },
    "52": {
        "English_v1": "hertclavre",
        "Latin_v1": "anedus"
    },
    "53": {
        "English_v1": "cipe",
        "Latin_v1": "acolonia"
    },
    "54": {
        "English_v1": "feldwort",
        "Latin_v1": "agrimonia"
    },
    "55": {
        "English_v1": "mersmalue",
        "Latin_v1": "althea eviscum"
    },
    "56": {
        "English_v1": "weremod",
        "Latin_v1": "absinthium"
    },
    "57": {
        "English_v1": "smalþistel",
        "Latin_v1": "anteleuce"
    },
    "58": {
        "English_v1": "clive",
        "Latin_v1": "apparina"
    },
    "59": {
        "English_v1": "madere",
        "Latin_v1": "anchorum"
    },
    "60": {
        "English_v1": "wodemerche",
        "Latin_v1": "apis silvestica"
    },
    "61": {
        "English_v1": "smynte",
        "Latin_v1": "althee"
    },
    "62": {
        "English_v1": "suþrenewode",
        "Latin_v1": "abrotanum"
    },
    "63": {
        "English_v1": "huate",
        "Latin_v1": "alphitum"
    },
    "64": {
        "English_v1": "tunmerche",
        "Latin_v1": "alexandria"
    },
    "65": {
        "English_v1": "genus frumenti",
        "Latin_v1": "alica"
    },
    "66": {
        "English_v1": "swinesnhep",
        "Latin_v1": "anagallis"
    },
    "67": {
        "English_v1": "swinesnhep",
        "Latin_v1": "acantes"
    },
    "68": {
        "English_v1": "juniperi fructus",
        "Latin_v1": "ariotidas"
    },
    "69": {
        "English_v1": "soot",
        "Latin_v1": "asboli"
    },
    "70": {
        "English_v1": "orpiment",
        "Latin_v1": "arsenicon"
    },
    "71": {
        "English_v1": "bromesrote",
        "Latin_v1": "aspactu"
    },
    "72": {
        "English_v1": "pyonie",
        "Latin_v1": "alief(l)os"
    },
    "73": {
        "English_v1": "dragaunce",
        "Latin_v1": "asclepis"
    },
    "74": {
        "English_v1": "wylde popy",
        "Latin_v1": "almones"
    },
    "75": {
        "English_v1": "elren",
        "Latin_v1": "sambucus"
    },
    "76": {
        "English_v1": "yerdgalle",
        "Latin_v1": "assarum"
    },
    "77": {
        "English_v1": "popy",
        "Latin_v1": "affodillus"
    },
    "78": {
        "English_v1": "brenemele",
        "Latin_v1": "alphita"
    },
    "79": {
        "English_v1": "elrenblosme",
        "Latin_v1": "antierotis"
    },
    "80": {
        "English_v1": "laureole lef",
        "Latin_v1": "alipiados"
    },
    "81": {
        "English_v1": "gladene",
        "Latin_v1": "affiradix"
    },
    "82": {
        "English_v1": "hennebane",
        "Latin_v1": "altercus"
    },
    "83": {
        "English_v1": "hennebane",
        "Latin_v1": "assuetus"
    },
    "84": {
        "English_v1": "smal salt",
        "Latin_v1": "aloxantus"
    },
    "85": {
        "English_v1": "moderwort",
        "Latin_v1": "ameracii"
    },
    "86": {
        "English_v1": "moderwort",
        "Latin_v1": "ampelo melinas"
    },
    "87": {
        "English_v1": "senlei~ sed",
        "Latin_v1": "agnis sperma"
    },
    "88": {
        "English_v1": "siþeshore",
        "Latin_v1": "apoquimatus"
    },
    "89": {
        "English_v1": "kockel",
        "Latin_v1": "agallis"
    },
    "90": {
        "English_v1": "pyonie",
        "Latin_v1": "algafotes"
    },
    "91": {
        "English_v1": "ayselle",
        "Latin_v1": "amantum"
    },
    "92": {
        "English_v1": "seal",
        "Latin_v1": "aguus"
    },
    "93": {
        "English_v1": "netlesed",
        "Latin_v1": "acalithis"
    },
    "94": {
        "English_v1": "puttoc",
        "Latin_v1": "accinos"
    },
    "95": {
        "English_v1": "moldewerp",
        "Latin_v1": "afalax"
    },
    "96": {
        "English_v1": "drasten of ely",
        "Latin_v1": "amirca"
    },
    "97": {
        "English_v1": "swnesfot",
        "Latin_v1": "astragulus"
    },
    "98": {
        "English_v1": "walewort",
        "Latin_v1": "amesate"
    },
    "99": {
        "English_v1": "malue",
        "Latin_v1": "acopon"
    },
    "100": {
        "English_v1": "wilfeldmor",
        "Latin_v1": "agriontaphilon"
    },
    "101": {
        "English_v1": "savyne",
        "Latin_v1": "antirina"
    },
    "102": {
        "English_v1": "thusondlef",
        "Latin_v1": "ambrosia"
    },
    "103": {
        "English_v1": "stanbreche",
        "Latin_v1": "adiantus"
    },
    "104": {
        "English_v1": "cloveþunge",
        "Latin_v1": "apium rusticum"
    },
    "105": {
        "English_v1": "pyonie",
        "Latin_v1": "aglaofatis"
    },
    "106": {
        "English_v1": "wilde sarfe",
        "Latin_v1": "ampeleleucum"
    },
    "107": {
        "English_v1": "lavre",
        "Latin_v1": "accorum",
        "Latin_v2": "affrodisia"
    },
    "108": {
        "English_v1": "seuulile",
        "Latin_v1": "aspiagme"
    },
    "109": {
        "English_v1": "garlek",
        "Latin_v1": "allium"
    },
    "110": {
        "English_v1": "dragaunce",
        "Latin_v1": "asclepias"
    },
    "111": {
        "English_v1": "haselnote",
        "Latin_v1": "avellana"
    },
    "112": {
        "English_v1": "walnote",
        "Latin_v1": "amigdola"
    },
    "113": {
        "English_v1": "reste",
        "Latin_v1": "anesis"
    },
    "114": {
        "English_v1": "gorclive",
        "Latin_v1": "agrimonia"
    },
    "115": {
        "English_v1": "senevey",
        "Latin_v1": "aron senapionis"
    },
    "116": {
        "English_v1": "scrippe",
        "Latin_v1": "apidia"
    },
    "117": {
        "English_v1": "mildwort",
        "Latin_v1": "asplenum"
    },
    "118": {
        "English_v1": "camomilla",
        "Latin_v1": "antemum"
    },
    "119": {
        "English_v1": "sinfulle",
        "Latin_v1": "acidula"
    },
    "120": {
        "English_v1": "gritte",
        "Latin_v1": "egriocananum"
    },
    "121": {
        "English_v1": "orpiment",
        "Latin_v1": "arsenium"
    },
    "122": {
        "English_v1": "tunder",
        "Latin_v1": "agaricum"
    },
    "123": {
        "Latin_v1": "affodillum:"
    },
    "124": {
        "English_v1": "parelee",
        "Latin_v1": "albucium"
    },
    "125": {
        "English_v1": "werte",
        "Latin_v1": "acrocordana"
    },
    "126": {
        "English_v1": "feldwort",
        "Latin_v1": "acrocerium"
    },
    "127": {
        "English_v1": "gallok",
        "Latin_v1": "adriaca"
    },
    "128": {
        "English_v1": "culnerebac",
        "Latin_v1": "argitilla"
    },
    "129": {
        "English_v1": "wodemarche",
        "Latin_v1": "apiaster"
    },
    "130": {
        "English_v1": "wilde redich",
        "Latin_v1": "aprirotarium"
    },
    "131": {
        "English_v1": "clote",
        "Latin_v1": "amorfilia"
    },
    "132": {
        "English_v1": "eferrote",
        "Latin_v1": "anta"
    },
    "133": {
        "English_v1": "escrote",
        "Latin_v1": "annuosa"
    },
    "134": {
        "English_v1": "eververn",
        "Latin_v1": "arboratica"
    },
    "135": {
        "English_v1": "flotwort",
        "Latin_v1": "algea"
    },
    "136": {
        "English_v1": "smerewort",
        "Latin_v1": "aristologia"
    },
    "137": {
        "English_v1": "idem",
        "Latin_v1": "absinuatica"
    },
    "138": {
        "English_v1": "walewort",
        "Latin_v1": "allevuus"
    },
    "139": {
        "English_v1": "unf(r)ordtrede",
        "Latin_v1": "appollogamus"
    },
    "140": {
        "English_v1": "crodwanbam",
        "Latin_v1": "ablacca"
    },
    "141": {
        "English_v1": "woderove",
        "Latin_v1": "astula regia"
    },
    "142": {
        "English_v1": "idem",
        "Latin_v1": "asphodillus"
    },
    "143": {
        "English_v1": "beowort",
        "Latin_v1": "aspiafucum"
    },
    "144": {
        "English_v1": "atterlothe",
        "Latin_v1": "astrilla"
    },
    "145": {
        "English_v1": "elm",
        "Latin_v1": "alumen"
    },
    "146": {
        "English_v1": "strue",
        "Latin_v1": "amigdalus"
    },
    "147": {
        "English_v1": "croppal",
        "Latin_v1": "acucule"
    },
    "148": {
        "English_v1": "hehlace",
        "Latin_v1": "archiatis"
    },
    "149": {
        "English_v1": "ramese",
        "Latin_v1": "acitellium"
    },
    "150": {
        "English_v1": "spelles appel",
        "Latin_v1": "arsenicocistis"
    },
    "151": {
        "English_v1": "autunon",
        "Latin_v1": "aspaltu"
    },
    "152": {
        "English_v1": "genciane",
        "Latin_v1": "basiliscus"
    },
    "153": {
        "English_v1": "wodeciervele",
        "Latin_v1": "brassica"
    },
    "154": {
        "English_v1": "lache",
        "Latin_v1": "bidella"
    },
    "155": {
        "English_v1": "wilde bete",
        "Latin_v1": "britonica"
    },
    "156": {
        "English_v1": "cal",
        "Latin_v1": "bletus"
    },
    "157": {
        "English_v1": "mugwort",
        "Latin_v1": "butalmun agon"
    },
    "158": {
        "English_v1": "aecerne",
        "Latin_v1": "balanus"
    },
    "159": {
        "English_v1": "savyne",
        "Latin_v1": "brateon"
    },
    "160": {
        "English_v1": "lupinesblosme",
        "Latin_v1": "bulbus studium"
    },
    "161": {
        "English_v1": "oxetunge",
        "Latin_v1": "buglossa"
    },
    "162": {
        "English_v1": "sauge",
        "Latin_v1": "briu"
    },
    "163": {
        "English_v1": "horsehove",
        "Latin_v1": "becicon"
    },
    "164": {
        "English_v1": "wynberieblosme",
        "Latin_v1": "bania"
    },
    "165": {
        "English_v1": "ate",
        "Latin_v1": "bromus"
    },
    "166": {
        "English_v1": "laureberie",
        "Latin_v1": "baca"
    },
    "167": {
        "English_v1": "redich",
        "English_v2": "nep",
        "Latin_v1": "bacanum"
    },
    "168": {
        "English_v1": "riercestan",
        "Latin_v1": "besed"
    },
    "169": {
        "English_v1": "oxeshege",
        "Latin_v1": "butalmum"
    },
    "170": {
        "English_v1": "þistelblosme",
        "Latin_v1": "boreo"
    },
    "171": {
        "English_v1": "horsmynte",
        "Latin_v1": "balsamita"
    },
    "172": {
        "English_v1": "foxesglove",
        "Latin_v1": "buglossa"
    },
    "173": {
        "English_v1": "berige",
        "Latin_v1": "bacinia"
    },
    "174": {
        "English_v1": "mayþe",
        "Latin_v1": "beneolente"
    },
    "175": {
        "English_v1": "clofwort",
        "Latin_v1": "batracion"
    },
    "176": {
        "English_v1": "hindemayþe",
        "Latin_v1": "bucstalium"
    },
    "177": {
        "English_v1": "gre(n)tewort",
        "Latin_v1": "beriballum"
    },
    "178": {
        "English_v1": "betonye",
        "Latin_v1": "betonica"
    },
    "179": {
        "English_v1": "wodecervele",
        "Latin_v1": "brassica"
    },
    "180": {
        "English_v1": "synegrene",
        "Latin_v1": "barba jovis"
    },
    "181": {
        "English_v1": "stanmerchesede",
        "Latin_v1": "bonades"
    },
    "182": {
        "English_v1": "kufetwort",
        "Latin_v1": "brionia"
    },
    "183": {
        "English_v1": "hundestunge",
        "Latin_v1": "beteta"
    },
    "184": {
        "English_v1": "brimstan",
        "Latin_v1": "bitumen"
    },
    "185": {
        "English_v1": "rudewort",
        "Latin_v1": "bilala"
    },
    "186": {
        "English_v1": "bremelberie",
        "Latin_v1": "batus"
    },
    "187": {
        "English_v1": "safis",
        "Latin_v1": "buniodes"
    },
    "188": {
        "English_v1": "frosca",
        "English_v2": "rana",
        "Latin_v1": "botrocos"
    },
    "189": {
        "English_v1": "merchessed",
        "Latin_v1": "bonades"
    },
    "190": {
        "English_v1": "sauge",
        "Latin_v1": "becion"
    },
    "191": {
        "English_v1": "þistelblosme",
        "Latin_v1": "beseon"
    },
    "192": {
        "English_v1": "hundredlef",
        "Latin_v1": "balaustia"
    },
    "193": {
        "English_v1": "hemeloc",
        "Latin_v1": "broina"
    },
    "194": {
        "English_v1": "calfrankis",
        "Latin_v1": "brassica"
    },
    "195": {
        "English_v1": "clote",
        "Latin_v1": "bletum"
    },
    "196": {
        "English_v1": "culeb",
        "Latin_v1": "britannica"
    },
    "197": {
        "English_v1": "hader",
        "Latin_v1": "brogus"
    },
    "198": {
        "English_v1": "efordrote",
        "Latin_v1": "boatium"
    },
    "199": {
        "English_v1": "aeswort",
        "Latin_v1": "berbenace"
    },
    "200": {
        "English_v1": "heope",
        "Latin_v1": "betunus"
    },
    "201": {
        "English_v1": "kirse",
        "Latin_v1": "britium"
    },
    "202": {
        "English_v1": "blakeberie",
        "Latin_v1": "bacina"
    },
    "203": {
        "English_v1": "gescatwort",
        "Latin_v1": "berbescum"
    },
    "204": {
        "English_v1": "cleate",
        "Latin_v1": "bardana"
    },
    "205": {
        "English_v1": "ribbewort",
        "Latin_v1": "cinoglorus"
    },
    "206": {
        "English_v1": "clote",
        "Latin_v1": "cliton"
    },
    "207": {
        "English_v1": "cirse",
        "Latin_v1": "cardamon"
    },
    "208": {
        "English_v1": "eordcrop",
        "Latin_v1": "camaleon"
    },
    "209": {
        "English_v1": "lebcorn",
        "Latin_v1": "catharticum"
    },
    "210": {
        "English_v1": "helenemore",
        "Latin_v1": "camerete"
    },
    "211": {
        "English_v1": "yerdgalle",
        "Latin_v1": "centaurea"
    },
    "212": {
        "English_v1": "thunga",
        "Latin_v1": "corsa"
    },
    "213": {
        "English_v1": "swetwort",
        "Latin_v1": "calitricem"
    },
    "214": {
        "English_v1": "celendre",
        "Latin_v1": "coliandrum"
    },
    "215": {
        "English_v1": "se brede",
        "Latin_v1": "camemelon"
    },
    "216": {
        "English_v1": "wodewistle",
        "Latin_v1": "cicuta"
    },
    "217": {
        "English_v1": "lovestiche",
        "Latin_v1": "coniee"
    },
    "218": {
        "English_v1": "wite clavere",
        "Latin_v1": "caceffa"
    },
    "219": {
        "English_v1": "slite",
        "Latin_v1": "ciclamina"
    },
    "220": {
        "English_v1": "red clavere",
        "Latin_v1": "calta"
    },
    "221": {
        "English_v1": "everefern",
        "Latin_v1": "colocus"
    },
    "222": {
        "English_v1": "swinescarse",
        "Latin_v1": "centenodia"
    },
    "223": {
        "English_v1": "synegrene",
        "Latin_v1": "colatidis"
    },
    "224": {
        "English_v1": "henep",
        "Latin_v1": "canafel"
    },
    "225": {
        "English_v1": "huit of lede",
        "Latin_v1": "cerussa"
    },
    "226": {
        "English_v1": "cycorie",
        "Latin_v1": "cicoria"
    },
    "227": {
        "English_v1": "pumyz",
        "Latin_v1": "citalos"
    },
    "228": {
        "English_v1": "creye",
        "Latin_v1": "cinolea"
    },
    "229": {
        "English_v1": "þistlesdust",
        "Latin_v1": "crustacimolea"
    },
    "230": {
        "English_v1": "elidegold",
        "Latin_v1": "cias"
    },
    "231": {
        "English_v1": "lindetwig",
        "Latin_v1": "canduelis"
    },
    "232": {
        "English_v1": "ealivre",
        "Latin_v1": "calitriscum"
    },
    "233": {
        "English_v1": "kinhbeam",
        "Latin_v1": "cariscus"
    },
    "234": {
        "English_v1": "wodewistle",
        "Latin_v1": "comui"
    },
    "235": {
        "English_v1": "wilde vetonie",
        "Latin_v1": "coceorion"
    },
    "236": {
        "English_v1": "ymglidegold",
        "Latin_v1": "cimbalatria"
    },
    "237": {
        "English_v1": "laureole sed",
        "Latin_v1": "cocoinidum"
    },
    "238": {
        "English_v1": "tunkarse",
        "Latin_v1": "carda(mo)mum"
    },
    "239": {
        "English_v1": "yvysed",
        "Latin_v1": "cissa"
    },
    "240": {
        "English_v1": "hundescive",
        "Latin_v1": "crommyrion"
    },
    "241": {
        "English_v1": "walewort",
        "Latin_v1": "capsitis"
    },
    "242": {
        "English_v1": "lilie",
        "Latin_v1": "crin(r)isleucorum",
        "Latin_v2": "lilium "
    },
    "243": {
        "English_v1": "wildefeldmore",
        "Latin_v1": "cariotas"
    },
    "244": {
        "English_v1": "betouneke",
        "Latin_v1": "cosmice"
    },
    "245": {
        "English_v1": "stanbreche",
        "Latin_v1": "colopendria"
    },
    "246": {
        "English_v1": "ybleche thistel",
        "Latin_v1": "cameleonta"
    },
    "247": {
        "English_v1": "ok appel",
        "Latin_v1": "crimaureos"
    },
    "248": {
        "English_v1": "ballocwort",
        "Latin_v1": "cicideros"
    },
    "249": {
        "English_v1": "wilde popy",
        "Latin_v1": "codion"
    },
    "250": {
        "English_v1": "lylie",
        "Latin_v1": "cronopos"
    },
    "251": {
        "English_v1": "popyesheved oþer blosme",
        "Latin_v1": "codia"
    },
    "252": {
        "English_v1": "horsefot",
        "Latin_v1": "ceforeos"
    },
    "253": {
        "English_v1": "brembelberie",
        "Latin_v1": "celtica"
    },
    "254": {
        "English_v1": "isoden stor",
        "Latin_v1": "colofonia"
    },
    "255": {
        "English_v1": "haselnote",
        "Latin_v1": "cariobasilicon"
    },
    "256": {
        "English_v1": "wilde þistel",
        "Latin_v1": "cirifolio"
    },
    "257": {
        "English_v1": "wilde þistel",
        "Latin_v1": "cacreos"
    },
    "258": {
        "English_v1": "ivi",
        "English_v2": "ciros",
        "English_v3": "clive",
        "Latin_v1": "crissocantus"
    },
    "259": {
        "English_v1": "laureole",
        "Latin_v1": "camela"
    },
    "260": {
        "English_v1": "mil",
        "Latin_v1": "centro"
    },
    "261": {
        "English_v1": "resse od the stor",
        "Latin_v1": "cipermii"
    },
    "262": {
        "English_v1": "criu",
        "Latin_v1": "crascii"
    },
    "263": {
        "English_v1": "thirstel",
        "Latin_v1": "cumario"
    },
    "264": {
        "English_v1": "wilde mente",
        "Latin_v1": "columbaria"
    },
    "265": {
        "English_v1": "culbeb oke",
        "Latin_v1": "camedreos"
    },
    "266": {
        "English_v1": "seg",
        "Latin_v1": "colena"
    },
    "267": {
        "English_v1": "witbeam",
        "Latin_v1": "catona"
    },
    "268": {
        "English_v1": "huite clavere",
        "Latin_v1": "citalona"
    },
    "269": {
        "English_v1": "liquorice",
        "Latin_v1": "cliriza"
    },
    "270": {
        "English_v1": "mayþe",
        "Latin_v1": "culuna"
    },
    "271": {
        "English_v1": "pyonesed",
        "Latin_v1": "clis"
    },
    "272": {
        "English_v1": "cirecped",
        "Latin_v1": "calamentis"
    },
    "273": {
        "English_v1": "walwort",
        "Latin_v1": "cameactis"
    },
    "274": {
        "English_v1": "nep",
        "Latin_v1": "congelidos"
    },
    "275": {
        "English_v1": "greshoppe",
        "Latin_v1": "carabus"
    },
    "276": {
        "English_v1": "ymolte pich",
        "Latin_v1": "cetria"
    },
    "277": {
        "English_v1": "netle",
        "Latin_v1": "cindelis"
    },
    "278": {
        "English_v1": "brom",
        "Latin_v1": "cetivi"
    },
    "279": {
        "English_v1": "wodewistlesed",
        "Latin_v1": "comospermaton"
    },
    "280": {
        "English_v1": "hoame",
        "Latin_v1": "canterides"
    },
    "281": {
        "English_v1": "snayl",
        "Latin_v1": "cheloni"
    },
    "282": {
        "English_v1": "reven",
        "Latin_v1": "corax"
    },
    "283": {
        "English_v1": "crowe",
        "Latin_v1": "corom"
    },
    "284": {
        "English_v1": "blac ivi",
        "Latin_v1": "cissos malus"
    },
    "285": {
        "English_v1": "þrostle",
        "Latin_v1": "cossifos"
    },
    "286": {
        "English_v1": "pye",
        "Latin_v1": "cissa"
    }
}