<?xml version='1.0' encoding='utf-8'?>
<text>
  <header>
    <author>Pond</author>
    <title>Almanack</title>
    <year>1688</year>
    <volume>-</volume>
    <pages>-</pages>
  </header>
  <content>
    <sentence id="s1">
      <token id="s1t1">POND</token>
      <token id="s1t2">M.</token>
      <token id="s1t3" rom_num="True">DC</token>
      <token id="s1t4">.</token>
    </sentence>
    <sentence id="s2">
      <token id="s2t1" rom_num="True">LXXXVIII</token>
      <token id="s2t2">.</token>
    </sentence>
    <sentence id="s3">
      <token id="s3t1">The</token>
      <token id="s3t2">latter</token>
      <token id="s3t3">part</token>
      <token id="s3t4">of</token>
      <token id="s3t5">this</token>
      <token id="s3t6">ALMANACK</token>
      <token id="s3t7">for</token>
      <token id="s3t8">the</token>
      <token id="s3t9">year</token>
      <token id="s3t10">of</token>
      <token id="s3t11">our</token>
      <token id="s3t12">LORD</token>
      <token id="s3t13">GOD</token>
      <token id="s3t14">1688</token>
      <token id="s3t15">.</token>
    </sentence>
    <sentence id="s4">
      <token id="s4t1">Being</token>
      <token id="s4t2">the</token>
      <token id="s4t3">Bissextile</token>
      <token id="s4t4">or</token>
      <token id="s4t5">Leap-year</token>
      <token id="s4t6">,</token>
      <token id="s4t7">and</token>
      <token id="s4t8">from</token>
      <token id="s4t9">the</token>
      <token id="s4t10">Conquest</token>
      <token id="s4t11">of</token>
      <token id="s4t12">England</token>
      <token id="s4t13">by</token>
      <token id="s4t14">William</token>
      <token id="s4t15">Duke</token>
      <token id="s4t16">of</token>
      <token id="s4t17">Normandy</token>
      <token id="s4t18">622</token>
      <token id="s4t19">years</token>
      <token id="s4t20">.</token>
    </sentence>
    <sentence id="s5">
      <token id="s5t1">Wherein</token>
      <token id="s5t2">is</token>
      <token id="s5t3">contained</token>
      <token id="s5t4">the</token>
      <token id="s5t5">Eclipses</token>
      <token id="s5t6">,</token>
      <token id="s5t7">with</token>
      <token id="s5t8">several</token>
      <token id="s5t9">usefull</token>
      <token id="s5t10">things</token>
      <token id="s5t11">and</token>
      <token id="s5t12">Tables</token>
      <token id="s5t13">,</token>
      <token id="s5t14">as</token>
      <token id="s5t15">a</token>
      <token id="s5t16">Table</token>
      <token id="s5t17">of</token>
      <token id="s5t18">all</token>
      <token id="s5t19">the</token>
      <token id="s5t20">Shires</token>
      <token id="s5t21">in</token>
      <token id="s5t22">England</token>
      <token id="s5t23">and</token>
      <token id="s5t24">Wales</token>
      <token id="s5t25">shewing</token>
      <token id="s5t26">how</token>
      <token id="s5t27">many</token>
      <token id="s5t28">Parliam</token>
      <token id="s5t29">.</token>
    </sentence>
    <sentence id="s6">
      <token id="s6t1">Men</token>
      <token id="s6t2">,</token>
      <token id="s6t3">Hundreds</token>
      <token id="s6t4">,</token>
      <token id="s6t5">&amp;c.</token>
      <token id="s6t6">are</token>
      <token id="s6t7">in</token>
      <token id="s6t8">each</token>
      <token id="s6t9">Shire</token>
      <token id="s6t10">,</token>
      <token id="s6t11">as</token>
      <token id="s6t12">also</token>
      <token id="s6t13">general</token>
      <token id="s6t14">Prognosticks</token>
      <token id="s6t15">of</token>
      <token id="s6t16">Pestilential</token>
      <token id="s6t17">years</token>
      <token id="s6t18">,</token>
      <token id="s6t19">and</token>
      <token id="s6t20">the</token>
      <token id="s6t21">Fairs</token>
      <token id="s6t22">in</token>
      <token id="s6t23">a</token>
      <token id="s6t24">larger</token>
      <token id="s6t25">manner</token>
      <token id="s6t26">than</token>
      <token id="s6t27">formerly</token>
      <token id="s6t28">.</token>
    </sentence>
    <sentence id="s7">
      <token id="s7t1">Frigidus</token>
      <token id="s7t2">&amp;</token>
      <token id="s7t3">siccus</token>
      <token id="s7t4">Satur</token>
      <token id="s7t5">.</token>
    </sentence>
    <sentence id="s8">
      <token id="s8t1">Jup.</token>
      <token id="s8t2" old_char="True">æstuat</token>
      <token id="s8t3">udus</token>
      <token id="s8t4">.</token>
    </sentence>
    <sentence id="s9">
      <token id="s9t1">Mars</token>
      <token id="s9t2">&amp;</token>
      <token id="s9t3">Sol</token>
      <token id="s9t4">sicci</token>
      <token id="s9t5">servent</token>
      <token id="s9t6">:</token>
      <token id="s9t7">sed</token>
      <token id="s9t8">,</token>
      <token id="s9t9">Luna</token>
      <token id="s9t10">Venusque</token>
      <token id="s9t11" old_char="True">Udæ</token>
      <token id="s9t12">frigescunt</token>
      <token id="s9t13">:</token>
      <token id="s9t14">medius</token>
      <token id="s9t15">Cyllenius</token>
      <token id="s9t16">esto</token>
      <token id="s9t17">.</token>
    </sentence>
    <sentence id="s10">
      <token id="s10t1">CAMBRIDGE</token>
      <token id="s10t2">,</token>
      <token id="s10t3">Printed</token>
      <token id="s10t4">by</token>
      <token id="s10t5">John</token>
      <token id="s10t6">Hayes</token>
      <token id="s10t7">Printer</token>
      <token id="s10t8">to</token>
      <token id="s10t9">the</token>
      <token id="s10t10">University</token>
      <token id="s10t11">.</token>
    </sentence>
    <sentence id="s11">
      <token id="s11t1">1688</token>
      <token id="s11t2">.</token>
    </sentence>
    <sentence id="s12">
      <token id="s12t1">Prognosticks</token>
      <token id="s12t2">of</token>
      <token id="s12t3">Pestilential</token>
      <token id="s12t4">and</token>
      <token id="s12t5">unwholsom</token>
      <token id="s12t6">Years</token>
      <token id="s12t7">.</token>
    </sentence>
    <sentence id="s13">
      <token id="s13t1">IT</token>
      <token id="s13t2">is</token>
      <token id="s13t3">observed</token>
      <token id="s13t4">by</token>
      <token id="s13t5">the</token>
      <token id="s13t6">Learned</token>
      <token id="s13t7">,</token>
      <token id="s13t8">that</token>
      <token id="s13t9">those</token>
      <token id="s13t10">Years</token>
      <token id="s13t11">Pestilential</token>
      <token id="s13t12">and</token>
      <token id="s13t13">unwholesom</token>
      <token id="s13t14">,</token>
      <token id="s13t15">when</token>
      <token id="s13t16">there</token>
      <token id="s13t17">are</token>
      <token id="s13t18">numbers</token>
      <token id="s13t19">of</token>
      <token id="s13t20">Frogs</token>
      <token id="s13t21">,</token>
      <token id="s13t22">Flies</token>
      <token id="s13t23">,</token>
      <token id="s13t24">Locusts</token>
      <token id="s13t25">,</token>
      <token id="s13t26">&amp;c.</token>
      <token id="s13t27">the</token>
      <token id="s13t28">reason</token>
      <token id="s13t29">because</token>
      <token id="s13t30">those</token>
      <token id="s13t31">Creatures</token>
      <token id="s13t32">being</token>
      <token id="s13t33">ingendred</token>
      <token id="s13t34">of</token>
      <token id="s13t35">put_ction</token>
      <token id="s13t36">,</token>
      <token id="s13t37">when</token>
      <token id="s13t38">they</token>
      <token id="s13t39">abound</token>
      <token id="s13t40">,</token>
      <token id="s13t41">shew</token>
      <token id="s13t42">a</token>
      <token id="s13t43">general</token>
      <token id="s13t44">disposi_</token>
      <token id="s13t45">of</token>
      <token id="s13t46">the</token>
      <token id="s13t47">Year</token>
      <token id="s13t48">,</token>
      <token id="s13t49">and</token>
      <token id="s13t50">constitution</token>
      <token id="s13t51">of</token>
      <token id="s13t52">the</token>
      <token id="s13t53">Air</token>
      <token id="s13t54">,</token>
      <token id="s13t55">to</token>
      <token id="s13t56">Disease</token>
      <token id="s13t57">of</token>
      <token id="s13t58">putrefaction</token>
      <token id="s13t59">:</token>
      <token id="s13t60">so</token>
      <token id="s13t61">likewise</token>
      <token id="s13t62">the</token>
      <token id="s13t63">same</token>
      <token id="s13t64">Prognostick_</token>
      <token id="s13t65">,</token>
      <token id="s13t66">if</token>
      <token id="s13t67">you</token>
      <token id="s13t68">find</token>
      <token id="s13t69">Worms</token>
      <token id="s13t70">in</token>
      <token id="s13t71">Oak</token>
      <token id="s13t72">Apples</token>
      <token id="s13t73">;</token>
      <token id="s13t74">for</token>
      <token id="s13t75">the</token>
      <token id="s13t76">constitution</token>
      <token id="s13t77">of</token>
      <token id="s13t78">the</token>
      <token id="s13t79">Air</token>
      <token id="s13t80">,</token>
      <token id="s13t81">appeareth</token>
      <token id="s13t82">more</token>
      <token id="s13t83">subtilly</token>
      <token id="s13t84">,</token>
      <token id="s13t85">in</token>
      <token id="s13t86">any</token>
      <token id="s13t87">of</token>
      <token id="s13t88">these</token>
      <token id="s13t89">things</token>
      <token id="s13t90">,</token>
      <token id="s13t91">than</token>
      <token id="s13t92">to</token>
      <token id="s13t93">the</token>
      <token id="s13t94">sence</token>
      <token id="s13t95">of</token>
      <token id="s13t96">Man.</token>
    </sentence>
    <sentence id="s14">
      <token id="s14t1">Great</token>
      <token id="s14t2">and</token>
      <token id="s14t3">early</token>
      <token id="s14t4">Heats</token>
      <token id="s14t5">in</token>
      <token id="s14t6">the</token>
      <token id="s14t7">Spring</token>
      <token id="s14t8">(</token>
      <token id="s14t9">and</token>
      <token id="s14t10">namely</token>
      <token id="s14t11">in</token>
      <token id="s14t12">May</token>
      <token id="s14t13">)</token>
      <token id="s14t14">without</token>
      <token id="s14t15">Winds</token>
      <token id="s14t16">,</token>
      <token id="s14t17">portend</token>
      <token id="s14t18">also</token>
      <token id="s14t19">pestilent</token>
      <token id="s14t20">Years</token>
      <token id="s14t21">and</token>
      <token id="s14t22">generally</token>
      <token id="s14t23">so</token>
      <token id="s14t24">do</token>
      <token id="s14t25">years</token>
      <token id="s14t26">with</token>
      <token id="s14t27">little</token>
      <token id="s14t28">Wind</token>
      <token id="s14t29">or</token>
      <token id="s14t30">Thunder</token>
      <token id="s14t31">.</token>
    </sentence>
    <sentence id="s15">
      <token id="s15t1">Great</token>
      <token id="s15t2">Drought</token>
      <token id="s15t3">also</token>
      <token id="s15t4">in</token>
      <token id="s15t5">Summer</token>
      <token id="s15t6">,</token>
      <token id="s15t7">continuing</token>
      <token id="s15t8">till</token>
      <token id="s15t9">_wards</token>
      <token id="s15t10">the</token>
      <token id="s15t11">end</token>
      <token id="s15t12">of</token>
      <token id="s15t13">August</token>
      <token id="s15t14">,</token>
      <token id="s15t15">and</token>
      <token id="s15t16">some</token>
      <token id="s15t17">gentle</token>
      <token id="s15t18">Showers</token>
      <token id="s15t19">upon</token>
      <token id="s15t20">them</token>
      <token id="s15t21">,</token>
      <token id="s15t22">and</token>
      <token id="s15t23">then</token>
      <token id="s15t24">some</token>
      <token id="s15t25">dry</token>
      <token id="s15t26">weather</token>
      <token id="s15t27">again</token>
      <token id="s15t28">;</token>
      <token id="s15t29">do</token>
      <token id="s15t30">_tend</token>
      <token id="s15t31">a</token>
      <token id="s15t32">pestilent</token>
      <token id="s15t33">Summer</token>
      <token id="s15t34">the</token>
      <token id="s15t35">year</token>
      <token id="s15t36">following</token>
      <token id="s15t37">:</token>
      <token id="s15t38">about</token>
      <token id="s15t39">the</token>
      <token id="s15t40">end</token>
      <token id="s15t41">of</token>
      <token id="s15t42">August</token>
      <token id="s15t43">,</token>
      <token id="s15t44">all</token>
      <token id="s15t45">the</token>
      <token id="s15t46">sweetness</token>
      <token id="s15t47">of</token>
      <token id="s15t48">the</token>
      <token id="s15t49">which</token>
      <token id="s15t50">goeth</token>
      <token id="s15t51">into</token>
      <token id="s15t52">Plants</token>
      <token id="s15t53">and</token>
      <token id="s15t54">Trees</token>
      <token id="s15t55">,</token>
      <token id="s15t56">is</token>
      <token id="s15t57">exhaled</token>
      <token id="s15t58">much</token>
      <token id="s15t59">more</token>
      <token id="s15t60">if</token>
      <token id="s15t61">August</token>
      <token id="s15t62">be</token>
      <token id="s15t63">dry</token>
      <token id="s15t64">)</token>
      <token id="s15t65">so</token>
      <token id="s15t66">that</token>
      <token id="s15t67">then</token>
      <token id="s15t68">breath</token>
      <token id="s15t69">forth</token>
      <token id="s15t70">of</token>
      <token id="s15t71">the</token>
      <token id="s15t72">Earth</token>
      <token id="s15t73">,</token>
      <token id="s15t74">but</token>
      <token id="s15t75">a</token>
      <token id="s15t76">gross</token>
      <token id="s15t77">Vapor</token>
      <token id="s15t78">w_</token>
      <token id="s15t79">apt</token>
      <token id="s15t80">to</token>
      <token id="s15t81">corrupt</token>
      <token id="s15t82">the</token>
      <token id="s15t83">Air</token>
      <token id="s15t84">:</token>
      <token id="s15t85">and</token>
      <token id="s15t86">that</token>
      <token id="s15t87">Vapor</token>
      <token id="s15t88">by</token>
      <token id="s15t89">the</token>
      <token id="s15t90">Showers</token>
      <token id="s15t91">,</token>
      <token id="s15t92">if</token>
      <token id="s15t93">they</token>
      <token id="s15t94">be</token>
      <token id="s15t95">gentle</token>
      <token id="s15t96">,</token>
      <token id="s15t97">is</token>
      <token id="s15t98">released</token>
      <token id="s15t99">,</token>
      <token id="s15t100">and</token>
      <token id="s15t101">co_</token>
      <token id="s15t102">forth</token>
      <token id="s15t103">abundantly</token>
      <token id="s15t104">:</token>
      <token id="s15t105">therefore</token>
      <token id="s15t106">they</token>
      <token id="s15t107">that</token>
      <token id="s15t108">come</token>
      <token id="s15t109">soon</token>
      <token id="s15t110">after</token>
      <token id="s15t111">those</token>
      <token id="s15t112">Showers</token>
      <token id="s15t113">are</token>
      <token id="s15t114">commonly</token>
      <token id="s15t115">taken</token>
      <token id="s15t116">Sickness</token>
      <token id="s15t117">.</token>
    </sentence>
    <sentence id="s16">
      <token id="s16t1">And</token>
      <token id="s16t2">in</token>
      <token id="s16t3">Africk</token>
      <token id="s16t4">,</token>
      <token id="s16t5">no</token>
      <token id="s16t6">body</token>
      <token id="s16t7">will</token>
      <token id="s16t8">stir</token>
      <token id="s16t9">out</token>
      <token id="s16t10">of</token>
      <token id="s16t11">after</token>
      <token id="s16t12">the</token>
      <token id="s16t13">first</token>
      <token id="s16t14">Showers</token>
      <token id="s16t15">:</token>
      <token id="s16t16">but</token>
      <token id="s16t17">if</token>
      <token id="s16t18">the</token>
      <token id="s16t19">Showers</token>
      <token id="s16t20">come</token>
      <token id="s16t21">_mently</token>
      <token id="s16t22">,</token>
      <token id="s16t23">than</token>
      <token id="s16t24">they</token>
      <token id="s16t25">rather</token>
      <token id="s16t26">wash</token>
      <token id="s16t27">and</token>
      <token id="s16t28">fill</token>
      <token id="s16t29">the</token>
      <token id="s16t30">Earth</token>
      <token id="s16t31">,</token>
      <token id="s16t32">give</token>
      <token id="s16t33">it</token>
      <token id="s16t34">leave</token>
      <token id="s16t35">to</token>
      <token id="s16t36">breath</token>
      <token id="s16t37">forth</token>
      <token id="s16t38">pleasantly</token>
      <token id="s16t39">.</token>
    </sentence>
    <sentence id="s17">
      <token id="s17t1">But</token>
      <token id="s17t2">if</token>
      <token id="s17t3">dry</token>
      <token id="s17t4">weather</token>
      <token id="s17t5">come</token>
      <token id="s17t6">again</token>
      <token id="s17t7">,</token>
      <token id="s17t8">than</token>
      <token id="s17t9">it</token>
      <token id="s17t10">fixeth</token>
      <token id="s17t11">and</token>
      <token id="s17t12">continueth</token>
      <token id="s17t13">the</token>
      <token id="s17t14">corruption</token>
      <token id="s17t15">of</token>
      <token id="s17t16">the</token>
      <token id="s17t17">Air</token>
      <token id="s17t18">,</token>
      <token id="s17t19">upon</token>
      <token id="s17t20">the</token>
      <token id="s17t21">first</token>
      <token id="s17t22">Showers</token>
      <token id="s17t23">begun</token>
      <token id="s17t24">,</token>
      <token id="s17t25">and</token>
      <token id="s17t26">maketh</token>
      <token id="s17t27">of</token>
      <token id="s17t28">it</token>
      <token id="s17t29">ill</token>
      <token id="s17t30">Influence</token>
      <token id="s17t31">,</token>
      <token id="s17t32">even</token>
      <token id="s17t33">to</token>
      <token id="s17t34">the</token>
      <token id="s17t35">next</token>
      <token id="s17t36">Summer</token>
      <token id="s17t37">,</token>
      <token id="s17t38">except</token>
      <token id="s17t39">a</token>
      <token id="s17t40">very</token>
      <token id="s17t41">frosty</token>
      <token id="s17t42">Winter</token>
      <token id="s17t43">discharge</token>
      <token id="s17t44">it</token>
      <token id="s17t45">,</token>
      <token id="s17t46">which</token>
      <token id="s17t47">seldom</token>
      <token id="s17t48">succeeds</token>
      <token id="s17t49">.</token>
    </sentence>
    <sentence id="s18">
      <token id="s18t1">The</token>
      <token id="s18t2">lesser</token>
      <token id="s18t3">Infection</token>
      <token id="s18t4">of</token>
      <token id="s18t5">the</token>
      <token id="s18t6">Small</token>
      <token id="s18t7">Pox</token>
      <token id="s18t8">,</token>
      <token id="s18t9">Purple</token>
      <token id="s18t10">-</token>
      <token id="s18t11">Feavers</token>
      <token id="s18t12">,</token>
      <token id="s18t13">Agues</token>
      <token id="s18t14">,</token>
      <token id="s18t15">in</token>
      <token id="s18t16">the</token>
      <token id="s18t17">Summer</token>
      <token id="s18t18">precedent</token>
      <token id="s18t19">,</token>
      <token id="s18t20">and</token>
      <token id="s18t21">hovering</token>
      <token id="s18t22">Winter</token>
      <token id="s18t23">,</token>
      <token id="s18t24">do</token>
      <token id="s18t25">likewise</token>
      <token id="s18t26">portend</token>
      <token id="s18t27">a</token>
      <token id="s18t28">great</token>
      <token id="s18t29">Pestilence</token>
      <token id="s18t30">in</token>
      <token id="s18t31">the</token>
      <token id="s18t32">Summer</token>
      <token id="s18t33">following</token>
      <token id="s18t34">;</token>
      <token id="s18t35">for</token>
      <token id="s18t36">putrefaction</token>
      <token id="s18t37">doth</token>
      <token id="s18t38">not</token>
      <token id="s18t39">rise</token>
      <token id="s18t40">its</token>
      <token id="s18t41">height</token>
      <token id="s18t42">at</token>
      <token id="s18t43">once</token>
      <token id="s18t44">.</token>
    </sentence>
    <sentence id="s19">
      <token id="s19t1">A</token>
      <token id="s19t2">dry</token>
      <token id="s19t3">March</token>
      <token id="s19t4">,</token>
      <token id="s19t5">and</token>
      <token id="s19t6">a</token>
      <token id="s19t7">dry</token>
      <token id="s19t8">May</token>
      <token id="s19t9">,</token>
      <token id="s19t10">portend</token>
      <token id="s19t11">a</token>
      <token id="s19t12">wholesom</token>
      <token id="s19t13">summer</token>
      <token id="s19t14">,</token>
      <token id="s19t15">if</token>
      <token id="s19t16">there</token>
      <token id="s19t17">be</token>
      <token id="s19t18">a</token>
      <token id="s19t19">showring</token>
      <token id="s19t20">April</token>
      <token id="s19t21">between</token>
      <token id="s19t22">:</token>
      <token id="s19t23">but</token>
      <token id="s19t24">otherwise</token>
      <token id="s19t25">it</token>
      <token id="s19t26">is</token>
      <token id="s19t27">a</token>
      <token id="s19t28">sign</token>
      <token id="s19t29">of</token>
      <token id="s19t30">a</token>
      <token id="s19t31">pestilential</token>
      <token id="s19t32">Year</token>
      <token id="s19t33">.</token>
    </sentence>
    <sentence id="s20">
      <token id="s20t1">Furthermore</token>
      <token id="s20t2">,</token>
      <token id="s20t3">because</token>
      <token id="s20t4">the</token>
      <token id="s20t5">Air</token>
      <token id="s20t6">according</token>
      <token id="s20t7">to</token>
      <token id="s20t8">its</token>
      <token id="s20t9">situation</token>
      <token id="s20t10">doth</token>
      <token id="s20t11">much</token>
      <token id="s20t12">alter</token>
      <token id="s20t13">and</token>
      <token id="s20t14">change</token>
      <token id="s20t15">the</token>
      <token id="s20t16">Constitution</token>
      <token id="s20t17">of</token>
      <token id="s20t18">body</token>
      <token id="s20t19">,</token>
      <token id="s20t20">and</token>
      <token id="s20t21">may</token>
      <token id="s20t22">breed</token>
      <token id="s20t23">pure</token>
      <token id="s20t24">and</token>
      <token id="s20t25">wholesom</token>
      <token id="s20t26">Bloud</token>
      <token id="s20t27">,</token>
      <token id="s20t28">corrupt</token>
      <token id="s20t29">and</token>
      <token id="s20t30">bad</token>
      <token id="s20t31">Bloud</token>
      <token id="s20t32">,</token>
      <token id="s20t33">and</token>
      <token id="s20t34">malignant</token>
      <token id="s20t35">Humors</token>
      <token id="s20t36">.</token>
    </sentence>
    <sentence id="s21">
      <token id="s21t1">_erefore</token>
      <token id="s21t2">that</token>
      <token id="s21t3">you</token>
      <token id="s21t4">may</token>
      <token id="s21t5">know</token>
      <token id="s21t6">what</token>
      <token id="s21t7">Air</token>
      <token id="s21t8">is</token>
      <token id="s21t9">pure</token>
      <token id="s21t10">and</token>
      <token id="s21t11">,</token>
      <token id="s21t12">and</token>
      <token id="s21t13">what</token>
      <token id="s21t14">air</token>
      <token id="s21t15">corrupt</token>
      <token id="s21t16">and</token>
      <token id="s21t17">infectious</token>
      <token id="s21t18">,</token>
      <token id="s21t19">we</token>
      <token id="s21t20">will</token>
      <token id="s21t21">ved</token>
      <token id="s21t22">,</token>
      <token id="s21t23">whereby</token>
      <token id="s21t24">you</token>
      <token id="s21t25">may</token>
      <token id="s21t26">conjecture</token>
      <token id="s21t27">how</token>
      <token id="s21t28">the</token>
      <token id="s21t29">Air</token>
      <token id="s21t30">is</token>
      <token id="s21t31">disposed</token>
      <token id="s21t32">;</token>
      <token id="s21t33">and</token>
      <token id="s21t34">that</token>
      <token id="s21t35">first</token>
      <token id="s21t36">,</token>
      <token id="s21t37">A</token>
      <token id="s21t38">sound</token>
      <token id="s21t39">anf</token>
      <token id="s21t40">pure</token>
      <token id="s21t41">Air</token>
      <token id="s21t42">is</token>
      <token id="s21t43">made</token>
      <token id="s21t44">hot</token>
      <token id="s21t45">presently</token>
      <token id="s21t46">after</token>
      <token id="s21t47">Sun</token>
      <token id="s21t48">,</token>
      <token id="s21t49">and</token>
      <token id="s21t50">is</token>
      <token id="s21t51">made</token>
      <token id="s21t52">cold</token>
      <token id="s21t53">presently</token>
      <token id="s21t54">after</token>
      <token id="s21t55">Sun-setting</token>
      <token id="s21t56">.</token>
    </sentence>
    <sentence id="s22">
      <token id="s22t1">Which</token>
      <token id="s22t2">yieldeth</token>
      <token id="s22t3">a</token>
      <token id="s22t4">pleasant</token>
      <token id="s22t5">smell</token>
      <token id="s22t6">after</token>
      <token id="s22t7">Rain</token>
      <token id="s22t8">,</token>
      <token id="s22t9">clear</token>
      <token id="s22t10">and</token>
      <token id="s22t11">not</token>
      <token id="s22t12">evaporated</token>
      <token id="s22t13">,</token>
      <token id="s22t14">open</token>
      <token id="s22t15">and</token>
      <token id="s22t16">lightsom</token>
      <token id="s22t17">,</token>
      <token id="s22t18">where</token>
      <token id="s22t19">the</token>
      <token id="s22t20">North</token>
      <token id="s22t21">wind</token>
      <token id="s22t22">bloweth</token>
      <token id="s22t23">,</token>
      <token id="s22t24">and</token>
      <token id="s22t25">where</token>
      <token id="s22t26">the</token>
      <token id="s22t27">East</token>
      <token id="s22t28">wind</token>
      <token id="s22t29">blow_</token>
      <token id="s22t30">in</token>
      <token id="s22t31">the</token>
      <token id="s22t32">morning</token>
      <token id="s22t33">.</token>
    </sentence>
    <sentence id="s23">
      <token id="s23t1">A</token>
      <token id="s23t2">corrupt</token>
      <token id="s23t3">and</token>
      <token id="s23t4">infectious</token>
      <token id="s23t5">Air</token>
      <token id="s23t6">,</token>
      <token id="s23t7">is</token>
      <token id="s23t8">made</token>
      <token id="s23t9">by</token>
      <token id="s23t10">the</token>
      <token id="s23t11">often</token>
      <token id="s23t12">of</token>
      <token id="s23t13">the</token>
      <token id="s23t14">South</token>
      <token id="s23t15">,</token>
      <token id="s23t16">or</token>
      <token id="s23t17">South</token>
      <token id="s23t18">-</token>
      <token id="s23t19">east</token>
      <token id="s23t20">-</token>
      <token id="s23t21">wind</token>
      <token id="s23t22">,</token>
      <token id="s23t23">or</token>
      <token id="s23t24">by</token>
      <token id="s23t25">the</token>
      <token id="s23t26">South-west</token>
      <token id="s23t27">,</token>
      <token id="s23t28">or</token>
      <token id="s23t29">West</token>
      <token id="s23t30">in</token>
      <token id="s23t31">the</token>
      <token id="s23t32">evening</token>
      <token id="s23t33">,</token>
      <token id="s23t34">which</token>
      <token id="s23t35">ingender</token>
      <token id="s23t36">Sicknesses</token>
      <token id="s23t37">.</token>
    </sentence>
    <sentence id="s24">
      <token id="s24t1">Where</token>
      <token id="s24t2">the</token>
      <token id="s24t3">Air</token>
      <token id="s24t4">is</token>
      <token id="s24t5">cold</token>
      <token id="s24t6">long</token>
      <token id="s24t7">after</token>
      <token id="s24t8">Sun-rising</token>
      <token id="s24t9">.</token>
    </sentence>
    <sentence id="s25">
      <token id="s25t1">Where</token>
      <token id="s25t2">the</token>
      <token id="s25t3">Air</token>
      <token id="s25t4">is</token>
      <token id="s25t5">long</token>
      <token id="s25t6">hot</token>
      <token id="s25t7">after</token>
      <token id="s25t8">Sun-set</token>
      <token id="s25t9">.</token>
    </sentence>
    <sentence id="s26">
      <token id="s26t1">Where</token>
      <token id="s26t2">the</token>
      <token id="s26t3">Air</token>
      <token id="s26t4">is</token>
      <token id="s26t5">long</token>
      <token id="s26t6">close</token>
      <token id="s26t7">,</token>
      <token id="s26t8">cloudy</token>
      <token id="s26t9">,</token>
      <token id="s26t10">or</token>
      <token id="s26t11">thick</token>
      <token id="s26t12">.</token>
    </sentence>
  </content>
</text>
